{
  "Rows": {
    "Count": 45
  },
  "Cols": {
    "Count": 60
  },
  "Values": {
    "1,1": "페이지3 - 탭2 (index 1로 표시될 페이지)"
  },
  "AttachInfos": {
    "3,1": {
      "CellType": {
        "$type": "Forguncy.ImageCellType, Forguncy",
        "UIPermissions": [
          {
            "Scope": 2,
            "AllowRoles": [
              "FGC_Anonymous"
            ]
          },
          {
            "Scope": 1,
            "AllowRoles": [
              "FGC_Anonymous"
            ]
          }
        ],
        "ImagePath": "logo-grapecity-sns.png"
      }
    }
  },
  "StyleDatas": {
    "Styles": [
      {
        "FontFamily": 0,
        "Formatter": 1
      }
    ],
    "Types": {
      "Strs": [
        "Body",
        "[AUTO]General"
      ]
    },
    "CellStyles": {
      "1,1": 0
    },
    "SheetStyle": {
      "FontFamily": 0
    }
  },
  "Spans": [
    "3,1,10,18"
  ],
  "PageInfo": {
    "$type": "Forguncy.Model.Pages.NormalPage, Forguncy",
    "AuthorizeInfo": {
      "VisitMode": 2
    }
  },
  "PrintInfo": {
    "Margin": {},
    "PaperSize": {}
  }
}